GC23100UNO/__init__.py
GC23100UNO/metodos_numericos.py
gc23100uno-0.1.0.dist-info/licenses/LICENSE
gc23100uno-0.1.0.dist-info/METADATA
gc23100uno-0.1.0.dist-info/WHEEL
gc23100uno-0.1.0.dist-info/top_level.txt
gc23100uno-0.1.0.dist-info/RECORD
